starcount/__init__.py
starcount/starcount.py
starcount-0.0.2.dist-info/LICENSE
starcount-0.0.2.dist-info/METADATA
starcount-0.0.2.dist-info/WHEEL
starcount-0.0.2.dist-info/entry_points.txt
starcount-0.0.2.dist-info/top_level.txt
starcount-0.0.2.dist-info/RECORD
