Metadata-Version: 2.1
Name: starcount
Version: 0.0.2
Summary: Command Line tool to get total stargazers count of GitHub Repository of any user.
Home-page: https://github.com/starkblaze01/Star-Count
Author: starkblaze01
Author-email: mp.pathela@gmail.com
License: MIT
Keywords: GitHub stargazers count stars-count repository
Platform: UNKNOWN
Classifier: Development Status :: 5 - Production/Stable
Classifier: Programming Language :: Python :: 3
Classifier: Programming Language :: Python :: 3.5
Classifier: Programming Language :: Python :: 3.6
Classifier: Programming Language :: Python :: 3.7
Classifier: Programming Language :: Python :: 3.8
Classifier: License :: OSI Approved :: MIT License
Classifier: Operating System :: Unix
Requires-Python: >=3.6
Requires-Dist: requests (>=2.22.0)
Requires-Dist: termcolor (>=1.1.0)
